pysarflow/__init__.py
pysarflow/grd.py
pysarflow/slc.py
pysarflow/utils.py
pysarflow-0.1.1.dist-info/METADATA
pysarflow-0.1.1.dist-info/WHEEL
pysarflow-0.1.1.dist-info/top_level.txt
pysarflow-0.1.1.dist-info/RECORD
