Metadata-Version: 2.4
Name: pysarflow
Version: 0.1.1
Summary: An open-source python library for SAR data processing
Author-email: Rabina Twayana <rabinatwayana123@gmail.com>, Omowonuola Akintola <wola.akintola@gmail.com>, Ethel Ogallo <ogalloethel@gmail.com>, Beatriz Perez <beatriz.bs.peres@gmail.com>
License: MIT
Project-URL: Documentation, https://rabinatwayana.github.io/pysarflow
Project-URL: Repository, https://github.com/rabinatwayana/pysarflow/
Keywords: sar,sarpy
Classifier: Natural Language :: English
Classifier: Programming Language :: Python :: 3.10
Classifier: License :: OSI Approved :: MIT License
Classifier: Operating System :: OS Independent
Requires-Python: <3.12.13,>=3.9.23
Requires-Dist: rasterio>=1.4.3
Requires-Dist: ipykernel>=6.29.5
Requires-Dist: pre-commit>=4.2.0
Requires-Dist: mkdocs-material>=9.6.14
Requires-Dist: mkdocs>=1.6.1
Requires-Dist: mdx-truly-sane-lists>=1.3
Requires-Dist: mkdocs-jupyter>=0.25.1
Requires-Dist: mkdocs-git-revision-date-localized-plugin>=1.4.5
Requires-Dist: mkdocstrings>=0.29.1
Requires-Dist: mkdocs-exclude>=1.0.2
Requires-Dist: mkdocstrings-python>=1.16.10
Requires-Dist: esa-snappy==1.0.9
Requires-Dist: matplotlib==3.9.4
Requires-Dist: pyshp==2.3.1
Requires-Dist: pygeoif==1.5.1
Requires-Dist: shapely==2.0.7
